olaf_the_beheader/__init__.py
olaf_the_beheader/__main__.py
olaf_the_beheader-0.1.2.dist-info/LICENSE
olaf_the_beheader-0.1.2.dist-info/METADATA
olaf_the_beheader-0.1.2.dist-info/WHEEL
olaf_the_beheader-0.1.2.dist-info/entry_points.txt
olaf_the_beheader-0.1.2.dist-info/top_level.txt
olaf_the_beheader-0.1.2.dist-info/RECORD
