Metadata-Version: 2.1
Name: olaf-the-beheader
Version: 0.1.2
Summary: OLAF BEHEAD PUNY FILES!
Home-page: https://github.com/etianen/olaf-the-beheader
Author: Dave Hall
Author-email: dave@etianen.com
License: BSD
Platform: UNKNOWN
